tickpy/__init__.py
tickpy/queue.py
tickpy/ticker.py
tickpy/timer.py
tickpy-0.6.0.dist-info/LICENSE
tickpy-0.6.0.dist-info/METADATA
tickpy-0.6.0.dist-info/WHEEL
tickpy-0.6.0.dist-info/RECORD
