Metadata-Version: 2.3
Name: tickpy
Version: 0.6.0
Summary: Timer classes with a focus on periodic timing in while loops
License: GPL-3.0-or-later
Keywords: timing,embedded,fsm
Author: Alex Byrne
Requires-Python: >=3.13
Classifier: License :: OSI Approved :: GNU General Public License v3 or later (GPLv3+)
Classifier: Programming Language :: Python :: 3
Classifier: Programming Language :: Python :: 3.13
Provides-Extra: pytest
Provides-Extra: pytest-cov
Requires-Dist: pytest (>=8.3.3) ; extra == "pytest"
Requires-Dist: pytest-cov (>=0.6.0) ; extra == "pytest-cov"
Project-URL: Homepage, https://github.com/blex-max/tickpy
